seestarpy/__init__.py
seestarpy/connection.py
seestarpy/data.py
seestarpy/event_watcher.py
seestarpy/observe.py
seestarpy/raw_commands.py
seestarpy/status.py
seestarpy/ui.py
seestarpy-0.1.0.dist-info/METADATA
seestarpy-0.1.0.dist-info/WHEEL
seestarpy-0.1.0.dist-info/licenses/LICENSE
seestarpy-0.1.0.dist-info/RECORD
